gitlabui/__init__.py
gitlabui/gitlab.py
gitlabui/views.py
gitlabui/static/favicon.svg
gitlabui/static/index.js
gitlabui/templates/index.html
gitlabui/templates/layout.html
gitlabui/templates/search.html
gitlabui-1.0.7.dist-info/METADATA
gitlabui-1.0.7.dist-info/WHEEL
gitlabui-1.0.7.dist-info/top_level.txt
gitlabui-1.0.7.dist-info/RECORD
