Metadata-Version: 2.1
Name: gitlabui
Version: 1.0.7
Summary: Flask App over Gitlab Api to browse projects tags and to search into repository files
Home-page: https://github.com/batou9150/gitlabui
Author: batou9150
License: UNKNOWN
Platform: UNKNOWN
Classifier: Programming Language :: Python :: 3
Classifier: Operating System :: OS Independent
Requires-Python: >=3.6
Requires-Dist: requests
Requires-Dist: requests-cache
Requires-Dist: flask
